{
  "xopenme": {
    "cus": {
      "include_name": "xopenme.h",
      "full_path": "/home/nikolay/CK-TOOLS/lib-rtl-xopenme-0.3-gcc-6.4.0-linux-64/lib/librtlxopenme.a",
      "used_package_uoa": "lib-rtl-xopenme",
      "version_split": [
        0,
        3
      ],
      "path_lib": "/home/nikolay/CK-TOOLS/lib-rtl-xopenme-0.3-gcc-6.4.0-linux-64/lib",
      "static_lib": "librtlxopenme.a",
      "used_package_uid": "0573487b8121d094",
      "env_prefix": "CK_ENV_LIB_RTL_XOPENME",
      "path_include": "/home/nikolay/CK-TOOLS/lib-rtl-xopenme-0.3-gcc-6.4.0-linux-64/include",
      "dynamic_lib": "librtlxopenme.so",
      "version": "0.3",
      "skip_path": "yes",
      "extra_dir": ""
    },
    "num_entries": 1,
    "sort": 100,
    "ver": "0.3",
    "choices": [
      "9a01a05a5c7569f7"
    ],
    "tags": "lib,xopenme",
    "bat": ". /home/nikolay/CK/local/env/9a01a05a5c7569f7/env.sh\n",
    "uoa": "9a01a05a5c7569f7",
    "dict": {
      "env": {
        "CK_ENV_LIB_RTL_XOPENME_DYNAMIC_NAME": "librtlxopenme.so",
        "CK_ENV_LIB_RTL_XOPENME_STATIC_NAME": "librtlxopenme.a",
        "CK_ENV_LIB_RTL_XOPENME": "/home/nikolay/CK-TOOLS/lib-rtl-xopenme-0.3-gcc-6.4.0-linux-64",
        "CK_ENV_LIB_RTL_XOPENME_INCLUDE_NAME": "xopenme.h"
      },
      "soft_uoa": "673507878d649b4a",
      "customize": {
        "include_name": "xopenme.h",
        "full_path": "/home/nikolay/CK-TOOLS/lib-rtl-xopenme-0.3-gcc-6.4.0-linux-64/lib/librtlxopenme.a",
        "used_package_uoa": "lib-rtl-xopenme",
        "version_split": [
          0,
          3
        ],
        "path_lib": "/home/nikolay/CK-TOOLS/lib-rtl-xopenme-0.3-gcc-6.4.0-linux-64/lib",
        "static_lib": "librtlxopenme.a",
        "used_package_uid": "0573487b8121d094",
        "env_prefix": "CK_ENV_LIB_RTL_XOPENME",
        "path_include": "/home/nikolay/CK-TOOLS/lib-rtl-xopenme-0.3-gcc-6.4.0-linux-64/include",
        "dynamic_lib": "librtlxopenme.so",
        "version": "0.3",
        "skip_path": "yes",
        "extra_dir": ""
      },
      "data_name": "xOpenME run-time library",
      "deps": {
        "compiler": {
          "bat": ". /home/nikolay/CK/local/env/9698607419bb66de/env.sh\n",
          "sort": 10,
          "ver": "6.4.0",
          "build_dir_name": "gcc",
          "choices": [
            "9698607419bb66de"
          ],
          "detected_ver": "6.4.0",
          "tags": "compiler,lang-c",
          "uoa": "9698607419bb66de",
          "dict": {
            "env": {
              "CK_FLAGS_DYNAMIC_BIN": " ",
              "CK_EXTRA_LIB_M": "-lm",
              "CK_FLAGS_STATIC_LIB": "-fPIC",
              "CK_COMPILER_FLAG_PTHREAD_LIB": "-lpthread",
              "CK_MAKE": "make",
              "CK_EXE_EXT": ".out",
              "CK_OPT_SPEED": "-O3",
              "CK_COMPILER_FLAG_OPENMP": "-fopenmp",
              "CK_ASM_EXT": ".s",
              "CK_LB_OUTPUT": "-o ",
              "CK_COMPILER_FLAG_CPP14": "-std=c++14",
              "CK_COMPILER_FLAG_CPP1Z": "-std=c++1z",
              "CK_FLAGS_CREATE_OBJ": "-c",
              "CK_FLAG_PREFIX_VAR": "-D",
              "CK_PROFILER": "gprof",
              "CK_GPROF_OUT_FILE": "gmon.out",
              "CK_DLL_EXT": ".so",
              "CK_OBJDUMP": "objdump -d",
              "CK_COMPILER_FLAG_CPP0X": "-std=c++0x",
              "CK_AR": "ar",
              "CK_FLAGS_CREATE_ASM": "-S",
              "CK_OPT_ALL_WARNINGS": "-Wall",
              "CK_LINKER_FLAG_OPENMP": "-lgomp -lrt",
              "CK_COMPILER_FLAG_STD90": "-std=c90",
              "CK_EXTRA_LIB_DL": "-ldl",
              "CK_LD": "ld",
              "CK_COMPILER_FLAGS_OBLIGATORY": "",
              "CK_RANLIB": "ranlib",
              "CK_COMPILER_FLAG_GPROF": "-pg",
              "CK_COMPILER_FLAG_STD99": "-std=c99",
              "CK_COMPILER_POSTFIX": "-6",
              "CK_CC": "gcc-6",
              "CK_FLAG_PREFIX_INCLUDE": "-I",
              "CK_ENV_COMPILER_GCC_LIB": "/usr/lib/gcc/x86_64-linux-gnu/6",
              "CK_FLAGS_STATIC_BIN": "-static -fPIC",
              "CK_LB": "ar rcs",
              "CK_OPT_SPEED_SAFE": "-O2",
              "CK_COMPILER_FLAG_PLUGIN": "-fplugin=",
              "CK_COMPILER_TOOLCHAIN_NAME": "gcc",
              "CK_LD_FLAGS_EXTRA": "",
              "CK_FLAGS_DLL": "-shared -fPIC",
              "CK_OBJ_EXT": ".o",
              "CK_CXX": "g++-6",
              "CK_OPT_UNWIND": " ",
              "CK_FLAG_PREFIX_LIB_DIR": "-L",
              "CK_FLAGS_OUTPUT": "-o ",
              "CK_OPT_SIZE": "-Os",
              "CK_ENV_COMPILER_GCC": "/usr",
              "CK_COMPILER_FLAG_CPP11": "-std=c++11",
              "CK_LIB_EXT": ".a",
              "CK_FLAGS_DLL_EXTRA": "",
              "CK_PLUGIN_FLAG": "-fplugin="
            },
            "soft_uoa": "3a8a82fa40bf992d",
            "customize": {
              "add_to_path": "yes",
              "soft_version_cmd": {
                "win": " --version > $#filename#$ 2>&1",
                "linux": "--version > $#filename#$ 2>&1"
              },
              "can_strip_dynamic_lib": "yes",
              "tool_prefix": "",
              "search_numeric_ext_on_linux": "yes",
              "build_dir_name": "gcc",
              "env_prefix": "CK_ENV_COMPILER_GCC",
              "tool_postfix": "-6",
              "retarget": "no",
              "ck_version": 10,
              "limit_recursion_dir_search": {
                "win": 4,
                "linux": 3
              },
              "version": "6.4.0",
              "full_path": "/usr/bin/gcc-6",
              "check_that_exists": "yes",
              "sort": 100,
              "tool_prefix_configured": "yes",
              "version_split": [
                6,
                4,
                0
              ],
              "soft_file": {
                "win": "gcc.exe",
                "linux": "gcc"
              },
              "add_only_with_version": "yes",
              "only_for_target_os_tags": [
                "mingw",
                "windows",
                "linux"
              ],
              "languages": [
                "C",
                "CPP"
              ],
              "soft_file_from_host_os": "yes",
              "tool_postfix_configured": "yes",
              "soft_path_example": {
                "win": "C:\\Program Files\\GCC-4.9.2-x64\\bin\\gcc.exe",
                "linux": "/usr/bin/gcc"
              },
              "skip_path": "yes"
            },
            "data_name": "GNU C compiler",
            "deps": {},
            "soft_alias": "compiler.gcc",
            "tags": [
              "64bits",
              "compiler",
              "gcc",
              "host-os-linux-64",
              "lang-c",
              "lang-cpp",
              "target-os-linux-64",
              "v6",
              "v6.4",
              "v6.4.0"
            ],
            "setup": {
              "version_split": [
                6,
                4,
                0
              ],
              "target_os_uoa": "4258b5fe54828a50",
              "version": "6.4.0",
              "host_os_uoa": "4258b5fe54828a50",
              "target_os_bits": "64"
            },
            "env_script": "env.sh"
          },
          "name": "C compiler",
          "num_entries": 1,
          "local": "yes"
        }
      },
      "tags": [
        "64bits",
        "channel-stable",
        "compiled-by-gcc",
        "compiled-by-gcc-6.4.0",
        "host-os-linux-64",
        "lang-c",
        "lang-cpp",
        "lang-f77",
        "lang-f90",
        "lang-f95",
        "lib",
        "rtl",
        "target-os-linux-64",
        "v0",
        "v0.3",
        "xopenme"
      ],
      "package_uoa": "0573487b8121d094",
      "soft_alias": "lib.rtl.xopenme",
      "setup": {
        "deps_compiler": "9698607419bb66de",
        "version_split": [
          0,
          3
        ],
        "target_os_uoa": "4258b5fe54828a50",
        "host_os_uoa": "4258b5fe54828a50",
        "target_os_bits": "64",
        "version": "0.3"
      },
      "env_script": "env.sh"
    },
    "name": "xOpenME library",
    "package_uoa": "0573487b8121d094",
    "local": "yes"
  },
  "compiler": {
    "cus": {
      "add_to_path": "yes",
      "soft_version_cmd": {
        "win": " --version > $#filename#$ 2>&1",
        "linux": "--version > $#filename#$ 2>&1"
      },
      "can_strip_dynamic_lib": "yes",
      "tool_prefix": "",
      "search_numeric_ext_on_linux": "yes",
      "build_dir_name": "gcc",
      "env_prefix": "CK_ENV_COMPILER_GCC",
      "tool_postfix": "-6",
      "retarget": "no",
      "ck_version": 10,
      "limit_recursion_dir_search": {
        "win": 4,
        "linux": 3
      },
      "version": "6.4.0",
      "full_path": "/usr/bin/gcc-6",
      "check_that_exists": "yes",
      "sort": 100,
      "tool_prefix_configured": "yes",
      "version_split": [
        6,
        4,
        0
      ],
      "soft_file": {
        "win": "gcc.exe",
        "linux": "gcc"
      },
      "add_only_with_version": "yes",
      "only_for_target_os_tags": [
        "mingw",
        "windows",
        "linux"
      ],
      "languages": [
        "C",
        "CPP"
      ],
      "soft_file_from_host_os": "yes",
      "tool_postfix_configured": "yes",
      "soft_path_example": {
        "win": "C:\\Program Files\\GCC-4.9.2-x64\\bin\\gcc.exe",
        "linux": "/usr/bin/gcc"
      },
      "skip_path": "yes"
    },
    "num_entries": 1,
    "sort": 0,
    "ver": "6.4.0",
    "build_dir_name": "gcc",
    "choices": [
      "9698607419bb66de"
    ],
    "detected_ver": "6.4.0",
    "tags": "compiler,lang-cpp",
    "bat": ". /home/nikolay/CK/local/env/9698607419bb66de/env.sh\n",
    "uoa": "9698607419bb66de",
    "dict": {
      "env": {
        "CK_FLAGS_DYNAMIC_BIN": " ",
        "CK_EXTRA_LIB_M": "-lm",
        "CK_FLAGS_STATIC_LIB": "-fPIC",
        "CK_COMPILER_FLAG_PTHREAD_LIB": "-lpthread",
        "CK_MAKE": "make",
        "CK_EXE_EXT": ".out",
        "CK_OPT_SPEED": "-O3",
        "CK_COMPILER_FLAG_OPENMP": "-fopenmp",
        "CK_ASM_EXT": ".s",
        "CK_LB_OUTPUT": "-o ",
        "CK_COMPILER_FLAG_CPP14": "-std=c++14",
        "CK_COMPILER_FLAG_CPP1Z": "-std=c++1z",
        "CK_FLAGS_CREATE_OBJ": "-c",
        "CK_FLAG_PREFIX_VAR": "-D",
        "CK_PROFILER": "gprof",
        "CK_GPROF_OUT_FILE": "gmon.out",
        "CK_DLL_EXT": ".so",
        "CK_OBJDUMP": "objdump -d",
        "CK_COMPILER_FLAG_CPP0X": "-std=c++0x",
        "CK_AR": "ar",
        "CK_FLAGS_CREATE_ASM": "-S",
        "CK_OPT_ALL_WARNINGS": "-Wall",
        "CK_LINKER_FLAG_OPENMP": "-lgomp -lrt",
        "CK_COMPILER_FLAG_STD90": "-std=c90",
        "CK_EXTRA_LIB_DL": "-ldl",
        "CK_LD": "ld",
        "CK_COMPILER_FLAGS_OBLIGATORY": "",
        "CK_RANLIB": "ranlib",
        "CK_COMPILER_FLAG_GPROF": "-pg",
        "CK_COMPILER_FLAG_STD99": "-std=c99",
        "CK_COMPILER_POSTFIX": "-6",
        "CK_CC": "gcc-6",
        "CK_FLAG_PREFIX_INCLUDE": "-I",
        "CK_ENV_COMPILER_GCC_LIB": "/usr/lib/gcc/x86_64-linux-gnu/6",
        "CK_FLAGS_STATIC_BIN": "-static -fPIC",
        "CK_LB": "ar rcs",
        "CK_OPT_SPEED_SAFE": "-O2",
        "CK_COMPILER_FLAG_PLUGIN": "-fplugin=",
        "CK_COMPILER_TOOLCHAIN_NAME": "gcc",
        "CK_LD_FLAGS_EXTRA": "",
        "CK_FLAGS_DLL": "-shared -fPIC",
        "CK_OBJ_EXT": ".o",
        "CK_CXX": "g++-6",
        "CK_OPT_UNWIND": " ",
        "CK_FLAG_PREFIX_LIB_DIR": "-L",
        "CK_FLAGS_OUTPUT": "-o ",
        "CK_OPT_SIZE": "-Os",
        "CK_ENV_COMPILER_GCC": "/usr",
        "CK_COMPILER_FLAG_CPP11": "-std=c++11",
        "CK_LIB_EXT": ".a",
        "CK_FLAGS_DLL_EXTRA": "",
        "CK_PLUGIN_FLAG": "-fplugin="
      },
      "soft_uoa": "3a8a82fa40bf992d",
      "customize": {
        "add_to_path": "yes",
        "soft_version_cmd": {
          "win": " --version > $#filename#$ 2>&1",
          "linux": "--version > $#filename#$ 2>&1"
        },
        "can_strip_dynamic_lib": "yes",
        "tool_prefix": "",
        "search_numeric_ext_on_linux": "yes",
        "build_dir_name": "gcc",
        "env_prefix": "CK_ENV_COMPILER_GCC",
        "tool_postfix": "-6",
        "retarget": "no",
        "ck_version": 10,
        "limit_recursion_dir_search": {
          "win": 4,
          "linux": 3
        },
        "version": "6.4.0",
        "full_path": "/usr/bin/gcc-6",
        "check_that_exists": "yes",
        "sort": 100,
        "tool_prefix_configured": "yes",
        "version_split": [
          6,
          4,
          0
        ],
        "soft_file": {
          "win": "gcc.exe",
          "linux": "gcc"
        },
        "add_only_with_version": "yes",
        "only_for_target_os_tags": [
          "mingw",
          "windows",
          "linux"
        ],
        "languages": [
          "C",
          "CPP"
        ],
        "soft_file_from_host_os": "yes",
        "tool_postfix_configured": "yes",
        "soft_path_example": {
          "win": "C:\\Program Files\\GCC-4.9.2-x64\\bin\\gcc.exe",
          "linux": "/usr/bin/gcc"
        },
        "skip_path": "yes"
      },
      "data_name": "GNU C compiler",
      "deps": {},
      "tags": [
        "64bits",
        "compiler",
        "gcc",
        "host-os-linux-64",
        "lang-c",
        "lang-cpp",
        "target-os-linux-64",
        "v6",
        "v6.4",
        "v6.4.0"
      ],
      "soft_alias": "compiler.gcc",
      "setup": {
        "version_split": [
          6,
          4,
          0
        ],
        "target_os_uoa": "4258b5fe54828a50",
        "version": "6.4.0",
        "host_os_uoa": "4258b5fe54828a50",
        "target_os_bits": "64"
      },
      "env_script": "env.sh"
    },
    "name": "C++ compiler",
    "local": "yes"
  },
  "library": {
    "cus": {
      "version": "1.7",
      "full_path": "/home/nikolay/CK-TOOLS/lib-tensorflow_cc-shared-1.7-gcc-6.4.0-linux-64/install/lib/tensorflow_cc/libtensorflow_cc.so",
      "used_package_uoa": "lib-tensorflow_cc-shared-1.7.0",
      "check_that_exists": "yes",
      "extra_dir": "",
      "path_lib": "/home/nikolay/CK-TOOLS/lib-tensorflow_cc-shared-1.7-gcc-6.4.0-linux-64/install/lib/tensorflow_cc",
      "used_package_uid": "c4baab22d1740334",
      "version_split": [
        1,
        7
      ],
      "soft_file": {
        "android": "tensorflow/contrib/makefile/gen/lib/libtensorflow-core.a",
        "linux": "install/lib/tensorflow_cc/libtensorflow_cc.so"
      },
      "env_prefix": "CK_ENV_LIB_TENSORFLOW_CC",
      "path_include": "/home/nikolay/CK-TOOLS/lib-tensorflow_cc-shared-1.7-gcc-6.4.0-linux-64/install/include/tensorflow",
      "dynamic_lib": "libtensorflow_cc.so",
      "ck_version": 10,
      "git_src_dir": "tensorflow_cc",
      "install_env": {
        "CK_CPU_ARM_VFPV3": "OFF",
        "CK_CXX_FLAGS_FOR_CMAKE_MINGW": "${CK_COMPILER_FLAGS_OBLIGATORY}",
        "CK_CXX_FLAGS_FOR_CMAKE": "${CK_COMPILER_FLAGS_OBLIGATORY}",
        "PACKAGE_GIT": "YES",
        "PACKAGE_URL": "https://github.com/ctuning/tensorflow_cc.git",
        "CK_TARGET_OS_ID": "linux",
        "CK_AR_PATH_FOR_CMAKE": "/usr/bin/ar",
        "CMAKE_CONFIG": "Release",
        "PACKAGE_SKIP_CMAKE_TARGET": "NO",
        "CK_HOST_OS_ID": "linux",
        "PACKAGE_CONFIGURE_FLAGS_LINUX": "",
        "CK_CMAKE_EXTRA": "",
        "CK_HOST_CPU_NUMBER_OF_PROCESSORS": "4",
        "PACKAGE_SKIP_CLEAN_SRC_DIR": "YES",
        "PACKAGE_SKIP_CLEAN_PACKAGE": "NO",
        "PACKAGE_CONFIGURE_FLAGS_ANDROID": "-DBUILD_SHARED_LIBS=OFF",
        "CK_TARGET_CPU_BITS": "64",
        "CK_CC_FLAGS_FOR_CMAKE": "${CK_COMPILER_FLAGS_OBLIGATORY}",
        "PACKAGE_BUILD_TYPE": "cmake",
        "CK_CC_PATH_FOR_CMAKE": "/usr/bin/gcc-6",
        "CK_CXX_PATH_FOR_CMAKE_MINGW": "/usr/bin/g++-6",
        "PACKAGE_VERSION": "1.7",
        "CK_CPU_ARM_NEON": "OFF",
        "CK_AR_PATH_FOR_CMAKE_MINGW": "/usr/bin/ar",
        "CK_ARMEABI_V7A": "OFF",
        "PACKAGE_PATCH": "YES",
        "PACKAGE_AUTOGEN": "NO",
        "PACKAGE_SUB_DIR": "tensorflow_cc",
        "CK_ARMEABI_V7A_HARD": "OFF",
        "CK_CXX_PATH_FOR_CMAKE": "/usr/bin/g++-6",
        "PACKAGE_CONFIGURE_FLAGS": "",
        "CK_CC_PATH_FOR_CMAKE_MINGW": "/usr/bin/gcc-6",
        "PACKAGE_CONFIGURE_FLAGS_WINDOWS": "",
        "CK_CC_FLAGS_FOR_CMAKE_MINGW": "${CK_COMPILER_FLAGS_OBLIGATORY}",
        "CK_COMPILER_PATH_FOR_CMAKE_MINGW": "/usr/bin",
        "PACKAGE_SKIP_CLEAN_OBJ": "YES",
        "CK_COMPILER_PATH_FOR_CMAKE": "/usr/bin",
        "PACKAGE_GIT_CHECKOUT": "lib-tensorflow_cc-shared-1.7.0",
        "PACKAGE_SUB_DIR1": "tensorflow_cc/tensorflow_cc",
        "PACKAGE_SKIP_CLEAN_INSTALL": "NO"
      },
      "skip_path": "yes",
      "limit_recursion_dir_search": {
        "win": 4,
        "linux": 5
      }
    },
    "num_entries": 4,
    "sort": -5,
    "ver": "1.7",
    "choices": [
      "f63a0b92934049ee",
      "42af974480b989d7",
      "e64ec4bca017b634",
      "613413998bfe81f9"
    ],
    "tags": "lib,tensorflow_cc",
    "bat": ". /home/nikolay/CK/local/env/f63a0b92934049ee/env.sh\n",
    "uoa": "f63a0b92934049ee",
    "dict": {
      "env": {
        "CK_ENV_LIB_TENSORFLOW_CC_LIBPROTOBUF": "/home/nikolay/CK-TOOLS/lib-tensorflow_cc-shared-1.7-gcc-6.4.0-linux-64/install/lib/tensorflow_cc/libprotobuf.a",
        "CK_ENV_LIB_TENSORFLOW_CC_INCLUDE5": "/home/nikolay/CK-TOOLS/lib-tensorflow_cc-shared-1.7-gcc-6.4.0-linux-64/install/include/tensorflow/tensorflow/contrib/makefile/gen/protobuf-host/include",
        "CK_ENV_LIB_TENSORFLOW_CC_INCLUDE6": "/home/nikolay/CK-TOOLS/lib-tensorflow_cc-shared-1.7-gcc-6.4.0-linux-64/install/include/tensorflow/tensorflow/contrib/makefile/downloads/nsync/public",
        "CK_ENV_LIB_TENSORFLOW_CC_LIBTENSORFLOW_CC": "/home/nikolay/CK-TOOLS/lib-tensorflow_cc-shared-1.7-gcc-6.4.0-linux-64/install/lib/tensorflow_cc/libtensorflow_cc.so",
        "CK_ENV_LIB_TENSORFLOW_CC_INCLUDE4": "/home/nikolay/CK-TOOLS/lib-tensorflow_cc-shared-1.7-gcc-6.4.0-linux-64/install/include/tensorflow/tensorflow/contrib/makefile/downloads/gemmlowp",
        "CK_ENV_LIB_TENSORFLOW_CC_CMAKE": "/home/nikolay/CK-TOOLS/lib-tensorflow_cc-shared-1.7-gcc-6.4.0-linux-64/install/cmake",
        "CK_ENV_LIB_TENSORFLOW_CC_INCLUDE2": "/home/nikolay/CK-TOOLS/lib-tensorflow_cc-shared-1.7-gcc-6.4.0-linux-64/install/include/tensorflow/tensorflow/contrib/makefile/downloads",
        "CK_ENV_LIB_TENSORFLOW_CC_INCLUDE3": "/home/nikolay/CK-TOOLS/lib-tensorflow_cc-shared-1.7-gcc-6.4.0-linux-64/install/include/tensorflow/tensorflow/contrib/makefile/downloads/eigen",
        "CK_ENV_LIB_TENSORFLOW_CC_INCLUDE1": "/home/nikolay/CK-TOOLS/lib-tensorflow_cc-shared-1.7-gcc-6.4.0-linux-64/install/include/tensorflow/bazel-genfiles",
        "CK_ENV_LIB_TENSORFLOW_CC": "/home/nikolay/CK-TOOLS/lib-tensorflow_cc-shared-1.7-gcc-6.4.0-linux-64",
        "CK_ENV_LIB_TENSORFLOW_CC_INCLUDE0": "/home/nikolay/CK-TOOLS/lib-tensorflow_cc-shared-1.7-gcc-6.4.0-linux-64/install/include/tensorflow"
      },
      "soft_uoa": "0cdc7594d430ab2b",
      "customize": {
        "version": "1.7",
        "full_path": "/home/nikolay/CK-TOOLS/lib-tensorflow_cc-shared-1.7-gcc-6.4.0-linux-64/install/lib/tensorflow_cc/libtensorflow_cc.so",
        "used_package_uoa": "lib-tensorflow_cc-shared-1.7.0",
        "check_that_exists": "yes",
        "extra_dir": "",
        "path_lib": "/home/nikolay/CK-TOOLS/lib-tensorflow_cc-shared-1.7-gcc-6.4.0-linux-64/install/lib/tensorflow_cc",
        "used_package_uid": "c4baab22d1740334",
        "version_split": [
          1,
          7
        ],
        "soft_file": {
          "android": "tensorflow/contrib/makefile/gen/lib/libtensorflow-core.a",
          "linux": "install/lib/tensorflow_cc/libtensorflow_cc.so"
        },
        "env_prefix": "CK_ENV_LIB_TENSORFLOW_CC",
        "path_include": "/home/nikolay/CK-TOOLS/lib-tensorflow_cc-shared-1.7-gcc-6.4.0-linux-64/install/include/tensorflow",
        "dynamic_lib": "libtensorflow_cc.so",
        "ck_version": 10,
        "git_src_dir": "tensorflow_cc",
        "install_env": {
          "CK_CPU_ARM_VFPV3": "OFF",
          "CK_CXX_FLAGS_FOR_CMAKE_MINGW": "${CK_COMPILER_FLAGS_OBLIGATORY}",
          "CK_CXX_FLAGS_FOR_CMAKE": "${CK_COMPILER_FLAGS_OBLIGATORY}",
          "PACKAGE_GIT": "YES",
          "PACKAGE_URL": "https://github.com/ctuning/tensorflow_cc.git",
          "CK_TARGET_OS_ID": "linux",
          "CK_AR_PATH_FOR_CMAKE": "/usr/bin/ar",
          "CMAKE_CONFIG": "Release",
          "PACKAGE_SKIP_CMAKE_TARGET": "NO",
          "CK_HOST_OS_ID": "linux",
          "PACKAGE_CONFIGURE_FLAGS_LINUX": "",
          "CK_CMAKE_EXTRA": "",
          "CK_HOST_CPU_NUMBER_OF_PROCESSORS": "4",
          "PACKAGE_SKIP_CLEAN_SRC_DIR": "YES",
          "PACKAGE_SKIP_CLEAN_PACKAGE": "NO",
          "PACKAGE_CONFIGURE_FLAGS_ANDROID": "-DBUILD_SHARED_LIBS=OFF",
          "CK_TARGET_CPU_BITS": "64",
          "CK_CC_FLAGS_FOR_CMAKE": "${CK_COMPILER_FLAGS_OBLIGATORY}",
          "PACKAGE_BUILD_TYPE": "cmake",
          "CK_CC_PATH_FOR_CMAKE": "/usr/bin/gcc-6",
          "CK_CXX_PATH_FOR_CMAKE_MINGW": "/usr/bin/g++-6",
          "PACKAGE_VERSION": "1.7",
          "CK_CPU_ARM_NEON": "OFF",
          "CK_AR_PATH_FOR_CMAKE_MINGW": "/usr/bin/ar",
          "CK_ARMEABI_V7A": "OFF",
          "PACKAGE_PATCH": "YES",
          "PACKAGE_AUTOGEN": "NO",
          "PACKAGE_SUB_DIR": "tensorflow_cc",
          "CK_ARMEABI_V7A_HARD": "OFF",
          "CK_CXX_PATH_FOR_CMAKE": "/usr/bin/g++-6",
          "PACKAGE_CONFIGURE_FLAGS": "",
          "CK_CC_PATH_FOR_CMAKE_MINGW": "/usr/bin/gcc-6",
          "PACKAGE_CONFIGURE_FLAGS_WINDOWS": "",
          "CK_CC_FLAGS_FOR_CMAKE_MINGW": "${CK_COMPILER_FLAGS_OBLIGATORY}",
          "CK_COMPILER_PATH_FOR_CMAKE_MINGW": "/usr/bin",
          "PACKAGE_SKIP_CLEAN_OBJ": "YES",
          "CK_COMPILER_PATH_FOR_CMAKE": "/usr/bin",
          "PACKAGE_GIT_CHECKOUT": "lib-tensorflow_cc-shared-1.7.0",
          "PACKAGE_SUB_DIR1": "tensorflow_cc/tensorflow_cc",
          "PACKAGE_SKIP_CLEAN_INSTALL": "NO"
        },
        "skip_path": "yes",
        "limit_recursion_dir_search": {
          "win": 4,
          "linux": 5
        }
      },
      "data_name": "TensorFlow C++ API",
      "deps": {
        "bazel": {
          "add_to_path": "no",
          "tags": "tool,bazel",
          "bat": ". /home/nikolay/CK/local/env/4f71be3142cc7170/env.sh\n",
          "sort": 40,
          "ver": "0.11.1",
          "build_dir_name": "bazel",
          "choices": [
            "4f71be3142cc7170",
            "5e7beacbfc2c1c47",
            "51d1316b040406f9"
          ],
          "detected_ver": "0.11.1",
          "num_entries": 1,
          "uoa": "4f71be3142cc7170",
          "dict": {
            "env": {
              "CK_ENV_TOOL_BAZEL_BIN": "/home/nikolay/CK-TOOLS/tool-bazel-0.11.1-linux-64/install/bin",
              "CK_ENV_TOOL_BAZEL": "/home/nikolay/CK-TOOLS/tool-bazel-0.11.1-linux-64/install"
            },
            "soft_uoa": "359f7730bd23ec60",
            "customize": {
              "only_for_host_os_tags": [
                "windows",
                "linux"
              ],
              "add_to_path": "yes",
              "soft_version_cmd": {
                "win": "version > $#filename#$ 2>&1",
                "linux": "version > $#filename#$ 2>&1"
              },
              "full_path": "/home/nikolay/CK-TOOLS/tool-bazel-0.11.1-linux-64/install/bin/bazel",
              "use_git_revision": "no",
              "check_that_exists": "yes",
              "extra_dir": "",
              "version": "0.11.1",
              "soft_file_from_host_os": "yes",
              "build_dir_name": "bazel",
              "used_package_uid": "1b43634cc2989a42",
              "soft_path_example": {
                "linux": "/usr/bin/bazel"
              },
              "version_split": [
                0,
                11,
                1
              ],
              "soft_file": {
                "win": "bazel.exe",
                "linux": "bazel"
              },
              "env_prefix": "CK_ENV_TOOL_BAZEL",
              "used_package_uoa": "1b43634cc2989a42",
              "install_env": {
                "CK_HOST_CPU_NUMBER_OF_PROCESSORS": "4",
                "BAZEL_URL": "https://github.com/bazelbuild/bazel/releases/download/0.11.1/bazel-0.11.1-dist.zip",
                "BAZEL_ZIP": "bazel-0.11.1-dist.zip",
                "BAZEL_PATCH4": "non-64bit-unix-warning.patch",
                "CK_TARGET_CPU_BITS": "64",
                "CK_TARGET_OS_ID": "linux",
                "BAZEL_PATCH3": "javac-max-heap-500mb.patch",
                "BAZEL_PATCH1": "aarch64.patch",
                "PACKAGE_VERSION": "0.11.1",
                "BAZEL_PATCH2": "aarch64-is-64bit.patch",
                "CK_HOST_OS_ID": "linux"
              },
              "git_src_dir": "src",
              "ck_version": 10,
              "skip_path": "yes",
              "limit_recursion_dir_search": {
                "win": 4,
                "linux": 4
              }
            },
            "data_name": "bazel",
            "deps": {
              "env-msys2": {
                "only_for_target_os_tags": [
                  "windows"
                ],
                "tags": "env,msys2",
                "local": "yes",
                "sort": 20,
                "name": "MSYS2 env"
              },
              "java-compiler": {
                "bat": ". /home/nikolay/CK/local/env/b118e295666b8e34/env.sh\n",
                "sort": 10,
                "ver": "1.8.0_121",
                "build_dir_name": "java",
                "choices": [
                  "b118e295666b8e34",
                  "802aa7e1cb04a1ca"
                ],
                "detected_ver": "1.8.0_121",
                "tags": "compiler,lang-java",
                "uoa": "b118e295666b8e34",
                "dict": {
                  "env": {
                    "CK_JAVAC": "javac",
                    "CK_OBJ_EXT": ".class",
                    "CK_FLAG_PREFIX_INCLUDE": "-classpath ",
                    "CK_JAVA_RT": "java -classpath .",
                    "CK_COMPILER_FLAGS_OBLIGATORY": "",
                    "CK_ENV_COMPILER_JAVA_BIN": "/home/nikolay/Programs/jdk1.8.0_121/bin",
                    "JAVA_HOME": "/home/nikolay/Programs/jdk1.8.0_121",
                    "CK_ENV_COMPILER_JAVA": "/home/nikolay/Programs/jdk1.8.0_121"
                  },
                  "soft_uoa": "0129a3b82235cbc0",
                  "customize": {
                    "add_to_path": "yes",
                    "soft_version_cmd": {
                      "win": "-version > $#filename#$ 2>&1",
                      "linux": "-version > $#filename#$ 2>&1"
                    },
                    "full_path": "/home/nikolay/Programs/jdk1.8.0_121/bin/javac",
                    "check_that_exists": "yes",
                    "soft_file_from_host_os": "yes",
                    "build_dir_name": "java",
                    "soft_path_example": {
                      "win": "C:\\Program Files\\Java\\jdk1.8.0_77\\bin\\javac.exe",
                      "linux": "/usr/bin/javac"
                    },
                    "version_split": [
                      1,
                      8,
                      0,
                      121
                    ],
                    "add_only_with_version": "yes",
                    "env_prefix": "CK_ENV_COMPILER_JAVA",
                    "only_for_target_os_tags": [
                      "windows",
                      "linux"
                    ],
                    "languages": [
                      "JAVA"
                    ],
                    "ck_version": 10,
                    "version": "1.8.0_121",
                    "soft_file": {
                      "win": "javac.exe",
                      "linux": "javac"
                    },
                    "skip_path": "yes",
                    "limit_recursion_dir_search": {
                      "win": 4,
                      "linux": 3
                    }
                  },
                  "data_name": "java compiler",
                  "deps": {},
                  "soft_alias": "compiler.java",
                  "tags": [
                    "64bits",
                    "compiler",
                    "host-os-linux-64",
                    "java",
                    "lang-java",
                    "target-os-linux-64",
                    "v1",
                    "v1.8",
                    "v1.8.0",
                    "v1.8.0.121"
                  ],
                  "setup": {
                    "version_split": [
                      1,
                      8,
                      0,
                      121
                    ],
                    "target_os_uoa": "4258b5fe54828a50",
                    "version": "1.8.0_121",
                    "host_os_uoa": "4258b5fe54828a50",
                    "target_os_bits": "64"
                  },
                  "env_script": "env.sh"
                },
                "name": "Java compiler",
                "num_entries": 1,
                "local": "yes"
              }
            },
            "soft_alias": "tool.bazel",
            "tags": [
              "64bits",
              "bazel",
              "channel-stable",
              "compiled-by-unknown_compiler",
              "compiled-by-unknown_compiler-unknown_version",
              "host-os-linux-64",
              "target-os-linux-64",
              "tool",
              "v0",
              "v0.11",
              "v0.11.1"
            ],
            "package_uoa": "1b43634cc2989a42",
            "setup": {
              "version_split": [
                0,
                11,
                1
              ],
              "target_os_uoa": "4258b5fe54828a50",
              "host_os_uoa": "4258b5fe54828a50",
              "deps_java-compiler": "b118e295666b8e34",
              "target_os_bits": "64",
              "version": "0.11.1"
            },
            "env_script": "env.sh"
          },
          "version_from": [
            0,
            5
          ],
          "name": "Bazel tool",
          "package_uoa": "1b43634cc2989a42",
          "version_to": [
            0,
            12,
            0
          ],
          "local": "no"
        },
        "cmake": {
          "force_target_as_host": "yes",
          "bat": ". /home/nikolay/CK/local/env/2564764d7438cbf6/env.sh\n",
          "sort": 5,
          "ver": "3.5.1",
          "build_dir_name": "cmake",
          "choices": [
            "2564764d7438cbf6"
          ],
          "detected_ver": "3.5.1",
          "tags": "tool,cmake",
          "uoa": "2564764d7438cbf6",
          "dict": {
            "env": {
              "CK_ENV_TOOL_CMAKE": "/usr",
              "CK_CMAKE": "cmake",
              "CK_ENV_TOOL_CMAKE_BIN": "/usr/bin"
            },
            "soft_uoa": "77ef5e31404d9589",
            "customize": {
              "only_for_host_os_tags": [
                "windows",
                "linux"
              ],
              "add_to_path": "yes",
              "soft_version_cmd": {
                "win": "--version > $#filename#$ 2>&1",
                "linux": "--version > $#filename#$ 2>&1"
              },
              "full_path": "/usr/bin/cmake",
              "check_that_exists": "yes",
              "version": "3.5.1",
              "build_dir_name": "cmake",
              "soft_path_example": {
                "win": "C:\\Program Files (x86)\\CMake\\bin\\cmake.exe",
                "linux": "/usr/bin/cmake"
              },
              "version_split": [
                3,
                5,
                1
              ],
              "soft_file": {
                "win": "cmake.exe",
                "linux": "cmake"
              },
              "env_prefix": "CK_ENV_TOOL_CMAKE",
              "ck_version": 10,
              "limit_recursion_dir_search": {
                "win": 3,
                "linux": 3
              },
              "soft_file_from_host_os": "yes",
              "skip_path": "yes",
              "add_only_with_version": "yes"
            },
            "data_name": "cmake",
            "deps": {},
            "soft_alias": "tool.cmake",
            "tags": [
              "64bits",
              "cmake",
              "host-os-linux-64",
              "target-os-linux-64",
              "tool",
              "v3",
              "v3.5",
              "v3.5.1"
            ],
            "setup": {
              "version_split": [
                3,
                5,
                1
              ],
              "target_os_uoa": "4258b5fe54828a50",
              "version": "3.5.1",
              "host_os_uoa": "4258b5fe54828a50",
              "target_os_bits": "64"
            },
            "env_script": "env.sh"
          },
          "name": "CMake",
          "num_entries": 1,
          "local": "yes"
        },
        "compiler": {
          "add_to_path": "no",
          "bat": ". /home/nikolay/CK/local/env/9698607419bb66de/env.sh\n",
          "sort": 10,
          "ver": "6.4.0",
          "build_dir_name": "gcc",
          "choices": [
            "9698607419bb66de"
          ],
          "detected_ver": "6.4.0",
          "tags": "compiler,lang-cpp",
          "uoa": "9698607419bb66de",
          "dict": {
            "env": {
              "CK_FLAGS_DYNAMIC_BIN": " ",
              "CK_EXTRA_LIB_M": "-lm",
              "CK_FLAGS_STATIC_LIB": "-fPIC",
              "CK_COMPILER_FLAG_PTHREAD_LIB": "-lpthread",
              "CK_MAKE": "make",
              "CK_EXE_EXT": ".out",
              "CK_OPT_SPEED": "-O3",
              "CK_COMPILER_FLAG_OPENMP": "-fopenmp",
              "CK_ASM_EXT": ".s",
              "CK_LB_OUTPUT": "-o ",
              "CK_COMPILER_FLAG_CPP14": "-std=c++14",
              "CK_COMPILER_FLAG_CPP1Z": "-std=c++1z",
              "CK_FLAGS_CREATE_OBJ": "-c",
              "CK_FLAG_PREFIX_VAR": "-D",
              "CK_PROFILER": "gprof",
              "CK_GPROF_OUT_FILE": "gmon.out",
              "CK_DLL_EXT": ".so",
              "CK_OBJDUMP": "objdump -d",
              "CK_COMPILER_FLAG_CPP0X": "-std=c++0x",
              "CK_AR": "ar",
              "CK_FLAGS_CREATE_ASM": "-S",
              "CK_OPT_ALL_WARNINGS": "-Wall",
              "CK_LINKER_FLAG_OPENMP": "-lgomp -lrt",
              "CK_COMPILER_FLAG_STD90": "-std=c90",
              "CK_EXTRA_LIB_DL": "-ldl",
              "CK_LD": "ld",
              "CK_COMPILER_FLAGS_OBLIGATORY": "",
              "CK_RANLIB": "ranlib",
              "CK_COMPILER_FLAG_GPROF": "-pg",
              "CK_COMPILER_FLAG_STD99": "-std=c99",
              "CK_COMPILER_POSTFIX": "-6",
              "CK_CC": "gcc-6",
              "CK_FLAG_PREFIX_INCLUDE": "-I",
              "CK_ENV_COMPILER_GCC_LIB": "/usr/lib/gcc/x86_64-linux-gnu/6",
              "CK_FLAGS_STATIC_BIN": "-static -fPIC",
              "CK_LB": "ar rcs",
              "CK_OPT_SPEED_SAFE": "-O2",
              "CK_COMPILER_FLAG_PLUGIN": "-fplugin=",
              "CK_COMPILER_TOOLCHAIN_NAME": "gcc",
              "CK_LD_FLAGS_EXTRA": "",
              "CK_FLAGS_DLL": "-shared -fPIC",
              "CK_OBJ_EXT": ".o",
              "CK_CXX": "g++-6",
              "CK_OPT_UNWIND": " ",
              "CK_FLAG_PREFIX_LIB_DIR": "-L",
              "CK_FLAGS_OUTPUT": "-o ",
              "CK_OPT_SIZE": "-Os",
              "CK_ENV_COMPILER_GCC": "/usr",
              "CK_COMPILER_FLAG_CPP11": "-std=c++11",
              "CK_LIB_EXT": ".a",
              "CK_FLAGS_DLL_EXTRA": "",
              "CK_PLUGIN_FLAG": "-fplugin="
            },
            "soft_uoa": "3a8a82fa40bf992d",
            "customize": {
              "add_to_path": "yes",
              "soft_version_cmd": {
                "win": " --version > $#filename#$ 2>&1",
                "linux": "--version > $#filename#$ 2>&1"
              },
              "can_strip_dynamic_lib": "yes",
              "tool_prefix": "",
              "search_numeric_ext_on_linux": "yes",
              "build_dir_name": "gcc",
              "env_prefix": "CK_ENV_COMPILER_GCC",
              "tool_postfix": "-6",
              "retarget": "no",
              "ck_version": 10,
              "limit_recursion_dir_search": {
                "win": 4,
                "linux": 3
              },
              "version": "6.4.0",
              "full_path": "/usr/bin/gcc-6",
              "check_that_exists": "yes",
              "sort": 100,
              "tool_prefix_configured": "yes",
              "version_split": [
                6,
                4,
                0
              ],
              "soft_file": {
                "win": "gcc.exe",
                "linux": "gcc"
              },
              "add_only_with_version": "yes",
              "only_for_target_os_tags": [
                "mingw",
                "windows",
                "linux"
              ],
              "languages": [
                "C",
                "CPP"
              ],
              "soft_file_from_host_os": "yes",
              "tool_postfix_configured": "yes",
              "soft_path_example": {
                "win": "C:\\Program Files\\GCC-4.9.2-x64\\bin\\gcc.exe",
                "linux": "/usr/bin/gcc"
              },
              "skip_path": "yes"
            },
            "data_name": "GNU C compiler",
            "deps": {},
            "soft_alias": "compiler.gcc",
            "tags": [
              "64bits",
              "compiler",
              "gcc",
              "host-os-linux-64",
              "lang-c",
              "lang-cpp",
              "target-os-linux-64",
              "v6",
              "v6.4",
              "v6.4.0"
            ],
            "setup": {
              "version_split": [
                6,
                4,
                0
              ],
              "target_os_uoa": "4258b5fe54828a50",
              "version": "6.4.0",
              "host_os_uoa": "4258b5fe54828a50",
              "target_os_bits": "64"
            },
            "env_script": "env.sh"
          },
          "name": "C++ compiler",
          "num_entries": 1,
          "local": "yes"
        }
      },
      "tags": [
        "64bits",
        "api",
        "bazel",
        "channel-stable",
        "compiled-by-gcc",
        "compiled-by-gcc-6.4.0",
        "host-os-linux-64",
        "lib",
        "target-os-linux-64",
        "tensorflow",
        "tensorflow_cc",
        "v1",
        "v1.7",
        "v1.7.0",
        "vmaster",
        "vshared",
        "vsrc"
      ],
      "package_uoa": "c4baab22d1740334",
      "soft_alias": "lib.tensorflow_cc",
      "setup": {
        "deps_compiler": "9698607419bb66de",
        "version_split": [
          1,
          7
        ],
        "target_os_uoa": "4258b5fe54828a50",
        "deps_cmake": "2564764d7438cbf6",
        "host_os_uoa": "4258b5fe54828a50",
        "deps_bazel": "4f71be3142cc7170",
        "target_os_bits": "64",
        "version": "1.7"
      },
      "env_script": "env.sh"
    },
    "name": "TensorFlow C++ API",
    "package_uoa": "c4baab22d1740334",
    "local": "yes"
  },
  "lib-nntest": {
    "cus": {
      "skip_add_to_path": "yes",
      "full_path": "/home/nikolay/CK-TOOLS/lib-nntest-0.1-gcc-6.4.0-linux-64/install/include/ck_nntest_common.h",
      "skip_add_to_bin": "yes",
      "used_package_uoa": "lib-nntest",
      "add_include_path": "yes",
      "version_split": [
        0,
        1
      ],
      "used_package_uid": "a6f6a5e9a44c7999",
      "env_prefix": "CK_ENV_LIB_NNTEST",
      "path_include": "/home/nikolay/CK-TOOLS/lib-nntest-0.1-gcc-6.4.0-linux-64/install/include",
      "version": "0.1",
      "limit_recursion_dir_search": {
        "win": 4,
        "linux": 4
      },
      "soft_file": {
        "win": "include\\ck_nntest_common.h",
        "linux": "include/ck_nntest_common.h"
      },
      "skip_path": "yes",
      "extra_dir": ""
    },
    "num_entries": 1,
    "sort": 2,
    "ver": "0.1",
    "choices": [
      "431181afddc0d160"
    ],
    "tags": "lib,nntest",
    "bat": ". /home/nikolay/CK/local/env/431181afddc0d160/env.sh\n",
    "uoa": "431181afddc0d160",
    "dict": {
      "env": {
        "CK_ENV_LIB_NNTEST": "/home/nikolay/CK-TOOLS/lib-nntest-0.1-gcc-6.4.0-linux-64/install"
      },
      "soft_uoa": "3f3beda1a806ad96",
      "customize": {
        "skip_add_to_path": "yes",
        "full_path": "/home/nikolay/CK-TOOLS/lib-nntest-0.1-gcc-6.4.0-linux-64/install/include/ck_nntest_common.h",
        "skip_add_to_bin": "yes",
        "used_package_uoa": "lib-nntest",
        "add_include_path": "yes",
        "version_split": [
          0,
          1
        ],
        "used_package_uid": "a6f6a5e9a44c7999",
        "env_prefix": "CK_ENV_LIB_NNTEST",
        "path_include": "/home/nikolay/CK-TOOLS/lib-nntest-0.1-gcc-6.4.0-linux-64/install/include",
        "version": "0.1",
        "limit_recursion_dir_search": {
          "win": 4,
          "linux": 4
        },
        "soft_file": {
          "win": "include\\ck_nntest_common.h",
          "linux": "include/ck_nntest_common.h"
        },
        "skip_path": "yes",
        "extra_dir": ""
      },
      "data_name": "NNTest library",
      "deps": {
        "compiler": {
          "bat": ". /home/nikolay/CK/local/env/9698607419bb66de/env.sh\n",
          "sort": 10,
          "ver": "6.4.0",
          "build_dir_name": "gcc",
          "choices": [
            "9698607419bb66de"
          ],
          "detected_ver": "6.4.0",
          "tags": "compiler,lang-cpp",
          "uoa": "9698607419bb66de",
          "dict": {
            "env": {
              "CK_FLAGS_DYNAMIC_BIN": " ",
              "CK_EXTRA_LIB_M": "-lm",
              "CK_FLAGS_STATIC_LIB": "-fPIC",
              "CK_COMPILER_FLAG_PTHREAD_LIB": "-lpthread",
              "CK_MAKE": "make",
              "CK_EXE_EXT": ".out",
              "CK_OPT_SPEED": "-O3",
              "CK_COMPILER_FLAG_OPENMP": "-fopenmp",
              "CK_ASM_EXT": ".s",
              "CK_LB_OUTPUT": "-o ",
              "CK_COMPILER_FLAG_CPP14": "-std=c++14",
              "CK_COMPILER_FLAG_CPP1Z": "-std=c++1z",
              "CK_FLAGS_CREATE_OBJ": "-c",
              "CK_FLAG_PREFIX_VAR": "-D",
              "CK_PROFILER": "gprof",
              "CK_GPROF_OUT_FILE": "gmon.out",
              "CK_DLL_EXT": ".so",
              "CK_OBJDUMP": "objdump -d",
              "CK_COMPILER_FLAG_CPP0X": "-std=c++0x",
              "CK_AR": "ar",
              "CK_FLAGS_CREATE_ASM": "-S",
              "CK_OPT_ALL_WARNINGS": "-Wall",
              "CK_LINKER_FLAG_OPENMP": "-lgomp -lrt",
              "CK_COMPILER_FLAG_STD90": "-std=c90",
              "CK_EXTRA_LIB_DL": "-ldl",
              "CK_LD": "ld",
              "CK_COMPILER_FLAGS_OBLIGATORY": "",
              "CK_RANLIB": "ranlib",
              "CK_COMPILER_FLAG_GPROF": "-pg",
              "CK_COMPILER_FLAG_STD99": "-std=c99",
              "CK_COMPILER_POSTFIX": "-6",
              "CK_CC": "gcc-6",
              "CK_FLAG_PREFIX_INCLUDE": "-I",
              "CK_ENV_COMPILER_GCC_LIB": "/usr/lib/gcc/x86_64-linux-gnu/6",
              "CK_FLAGS_STATIC_BIN": "-static -fPIC",
              "CK_LB": "ar rcs",
              "CK_OPT_SPEED_SAFE": "-O2",
              "CK_COMPILER_FLAG_PLUGIN": "-fplugin=",
              "CK_COMPILER_TOOLCHAIN_NAME": "gcc",
              "CK_LD_FLAGS_EXTRA": "",
              "CK_FLAGS_DLL": "-shared -fPIC",
              "CK_OBJ_EXT": ".o",
              "CK_CXX": "g++-6",
              "CK_OPT_UNWIND": " ",
              "CK_FLAG_PREFIX_LIB_DIR": "-L",
              "CK_FLAGS_OUTPUT": "-o ",
              "CK_OPT_SIZE": "-Os",
              "CK_ENV_COMPILER_GCC": "/usr",
              "CK_COMPILER_FLAG_CPP11": "-std=c++11",
              "CK_LIB_EXT": ".a",
              "CK_FLAGS_DLL_EXTRA": "",
              "CK_PLUGIN_FLAG": "-fplugin="
            },
            "soft_uoa": "3a8a82fa40bf992d",
            "customize": {
              "add_to_path": "yes",
              "soft_version_cmd": {
                "win": " --version > $#filename#$ 2>&1",
                "linux": "--version > $#filename#$ 2>&1"
              },
              "can_strip_dynamic_lib": "yes",
              "tool_prefix": "",
              "search_numeric_ext_on_linux": "yes",
              "build_dir_name": "gcc",
              "env_prefix": "CK_ENV_COMPILER_GCC",
              "tool_postfix": "-6",
              "retarget": "no",
              "ck_version": 10,
              "limit_recursion_dir_search": {
                "win": 4,
                "linux": 3
              },
              "version": "6.4.0",
              "full_path": "/usr/bin/gcc-6",
              "check_that_exists": "yes",
              "sort": 100,
              "tool_prefix_configured": "yes",
              "version_split": [
                6,
                4,
                0
              ],
              "soft_file": {
                "win": "gcc.exe",
                "linux": "gcc"
              },
              "add_only_with_version": "yes",
              "only_for_target_os_tags": [
                "mingw",
                "windows",
                "linux"
              ],
              "languages": [
                "C",
                "CPP"
              ],
              "soft_file_from_host_os": "yes",
              "tool_postfix_configured": "yes",
              "soft_path_example": {
                "win": "C:\\Program Files\\GCC-4.9.2-x64\\bin\\gcc.exe",
                "linux": "/usr/bin/gcc"
              },
              "skip_path": "yes"
            },
            "data_name": "GNU C compiler",
            "deps": {},
            "soft_alias": "compiler.gcc",
            "tags": [
              "64bits",
              "compiler",
              "gcc",
              "host-os-linux-64",
              "lang-c",
              "lang-cpp",
              "target-os-linux-64",
              "v6",
              "v6.4",
              "v6.4.0"
            ],
            "setup": {
              "version_split": [
                6,
                4,
                0
              ],
              "target_os_uoa": "4258b5fe54828a50",
              "version": "6.4.0",
              "host_os_uoa": "4258b5fe54828a50",
              "target_os_bits": "64"
            },
            "env_script": "env.sh"
          },
          "name": "C compiler",
          "num_entries": 1,
          "local": "yes"
        },
        "xopenme": {
          "dict": {
            "env": {
              "CK_ENV_LIB_RTL_XOPENME_DYNAMIC_NAME": "librtlxopenme.so",
              "CK_ENV_LIB_RTL_XOPENME_STATIC_NAME": "librtlxopenme.a",
              "CK_ENV_LIB_RTL_XOPENME": "/home/nikolay/CK-TOOLS/lib-rtl-xopenme-0.3-gcc-6.4.0-linux-64",
              "CK_ENV_LIB_RTL_XOPENME_INCLUDE_NAME": "xopenme.h"
            },
            "soft_uoa": "673507878d649b4a",
            "customize": {
              "include_name": "xopenme.h",
              "full_path": "/home/nikolay/CK-TOOLS/lib-rtl-xopenme-0.3-gcc-6.4.0-linux-64/lib/librtlxopenme.a",
              "used_package_uoa": "lib-rtl-xopenme",
              "version_split": [
                0,
                3
              ],
              "path_lib": "/home/nikolay/CK-TOOLS/lib-rtl-xopenme-0.3-gcc-6.4.0-linux-64/lib",
              "static_lib": "librtlxopenme.a",
              "used_package_uid": "0573487b8121d094",
              "env_prefix": "CK_ENV_LIB_RTL_XOPENME",
              "path_include": "/home/nikolay/CK-TOOLS/lib-rtl-xopenme-0.3-gcc-6.4.0-linux-64/include",
              "dynamic_lib": "librtlxopenme.so",
              "version": "0.3",
              "skip_path": "yes",
              "extra_dir": ""
            },
            "data_name": "xOpenME run-time library",
            "deps": {
              "compiler": {
                "bat": ". /home/nikolay/CK/local/env/9698607419bb66de/env.sh\n",
                "sort": 10,
                "ver": "6.4.0",
                "build_dir_name": "gcc",
                "choices": [
                  "9698607419bb66de"
                ],
                "detected_ver": "6.4.0",
                "tags": "compiler,lang-c",
                "uoa": "9698607419bb66de",
                "dict": {
                  "env": {
                    "CK_FLAGS_DYNAMIC_BIN": " ",
                    "CK_EXTRA_LIB_M": "-lm",
                    "CK_FLAGS_STATIC_LIB": "-fPIC",
                    "CK_COMPILER_FLAG_PTHREAD_LIB": "-lpthread",
                    "CK_MAKE": "make",
                    "CK_EXE_EXT": ".out",
                    "CK_OPT_SPEED": "-O3",
                    "CK_COMPILER_FLAG_OPENMP": "-fopenmp",
                    "CK_ASM_EXT": ".s",
                    "CK_LB_OUTPUT": "-o ",
                    "CK_COMPILER_FLAG_CPP14": "-std=c++14",
                    "CK_COMPILER_FLAG_CPP1Z": "-std=c++1z",
                    "CK_FLAGS_CREATE_OBJ": "-c",
                    "CK_FLAG_PREFIX_VAR": "-D",
                    "CK_PROFILER": "gprof",
                    "CK_GPROF_OUT_FILE": "gmon.out",
                    "CK_DLL_EXT": ".so",
                    "CK_OBJDUMP": "objdump -d",
                    "CK_COMPILER_FLAG_CPP0X": "-std=c++0x",
                    "CK_AR": "ar",
                    "CK_FLAGS_CREATE_ASM": "-S",
                    "CK_OPT_ALL_WARNINGS": "-Wall",
                    "CK_LINKER_FLAG_OPENMP": "-lgomp -lrt",
                    "CK_COMPILER_FLAG_STD90": "-std=c90",
                    "CK_EXTRA_LIB_DL": "-ldl",
                    "CK_LD": "ld",
                    "CK_COMPILER_FLAGS_OBLIGATORY": "",
                    "CK_RANLIB": "ranlib",
                    "CK_COMPILER_FLAG_GPROF": "-pg",
                    "CK_COMPILER_FLAG_STD99": "-std=c99",
                    "CK_COMPILER_POSTFIX": "-6",
                    "CK_CC": "gcc-6",
                    "CK_FLAG_PREFIX_INCLUDE": "-I",
                    "CK_ENV_COMPILER_GCC_LIB": "/usr/lib/gcc/x86_64-linux-gnu/6",
                    "CK_FLAGS_STATIC_BIN": "-static -fPIC",
                    "CK_LB": "ar rcs",
                    "CK_OPT_SPEED_SAFE": "-O2",
                    "CK_COMPILER_FLAG_PLUGIN": "-fplugin=",
                    "CK_COMPILER_TOOLCHAIN_NAME": "gcc",
                    "CK_LD_FLAGS_EXTRA": "",
                    "CK_FLAGS_DLL": "-shared -fPIC",
                    "CK_OBJ_EXT": ".o",
                    "CK_CXX": "g++-6",
                    "CK_OPT_UNWIND": " ",
                    "CK_FLAG_PREFIX_LIB_DIR": "-L",
                    "CK_FLAGS_OUTPUT": "-o ",
                    "CK_OPT_SIZE": "-Os",
                    "CK_ENV_COMPILER_GCC": "/usr",
                    "CK_COMPILER_FLAG_CPP11": "-std=c++11",
                    "CK_LIB_EXT": ".a",
                    "CK_FLAGS_DLL_EXTRA": "",
                    "CK_PLUGIN_FLAG": "-fplugin="
                  },
                  "soft_uoa": "3a8a82fa40bf992d",
                  "customize": {
                    "add_to_path": "yes",
                    "soft_version_cmd": {
                      "win": " --version > $#filename#$ 2>&1",
                      "linux": "--version > $#filename#$ 2>&1"
                    },
                    "can_strip_dynamic_lib": "yes",
                    "tool_prefix": "",
                    "search_numeric_ext_on_linux": "yes",
                    "build_dir_name": "gcc",
                    "env_prefix": "CK_ENV_COMPILER_GCC",
                    "tool_postfix": "-6",
                    "retarget": "no",
                    "ck_version": 10,
                    "limit_recursion_dir_search": {
                      "win": 4,
                      "linux": 3
                    },
                    "version": "6.4.0",
                    "full_path": "/usr/bin/gcc-6",
                    "check_that_exists": "yes",
                    "sort": 100,
                    "tool_prefix_configured": "yes",
                    "version_split": [
                      6,
                      4,
                      0
                    ],
                    "soft_file": {
                      "win": "gcc.exe",
                      "linux": "gcc"
                    },
                    "add_only_with_version": "yes",
                    "only_for_target_os_tags": [
                      "mingw",
                      "windows",
                      "linux"
                    ],
                    "languages": [
                      "C",
                      "CPP"
                    ],
                    "soft_file_from_host_os": "yes",
                    "tool_postfix_configured": "yes",
                    "soft_path_example": {
                      "win": "C:\\Program Files\\GCC-4.9.2-x64\\bin\\gcc.exe",
                      "linux": "/usr/bin/gcc"
                    },
                    "skip_path": "yes"
                  },
                  "data_name": "GNU C compiler",
                  "deps": {},
                  "soft_alias": "compiler.gcc",
                  "tags": [
                    "64bits",
                    "compiler",
                    "gcc",
                    "host-os-linux-64",
                    "lang-c",
                    "lang-cpp",
                    "target-os-linux-64",
                    "v6",
                    "v6.4",
                    "v6.4.0"
                  ],
                  "setup": {
                    "version_split": [
                      6,
                      4,
                      0
                    ],
                    "target_os_uoa": "4258b5fe54828a50",
                    "version": "6.4.0",
                    "host_os_uoa": "4258b5fe54828a50",
                    "target_os_bits": "64"
                  },
                  "env_script": "env.sh"
                },
                "name": "C compiler",
                "num_entries": 1,
                "local": "yes"
              }
            },
            "soft_alias": "lib.rtl.xopenme",
            "tags": [
              "64bits",
              "channel-stable",
              "compiled-by-gcc",
              "compiled-by-gcc-6.4.0",
              "host-os-linux-64",
              "lang-c",
              "lang-cpp",
              "lang-f77",
              "lang-f90",
              "lang-f95",
              "lib",
              "rtl",
              "target-os-linux-64",
              "v0",
              "v0.3",
              "xopenme"
            ],
            "package_uoa": "0573487b8121d094",
            "setup": {
              "deps_compiler": "9698607419bb66de",
              "version_split": [
                0,
                3
              ],
              "target_os_uoa": "4258b5fe54828a50",
              "host_os_uoa": "4258b5fe54828a50",
              "target_os_bits": "64",
              "version": "0.3"
            },
            "env_script": "env.sh"
          },
          "package_uoa": "0573487b8121d094",
          "ver": "0.3",
          "tags": "lib,xopenme",
          "bat": ". /home/nikolay/CK/local/env/9a01a05a5c7569f7/env.sh\n",
          "sort": 100,
          "local": "yes",
          "num_entries": 1,
          "name": "xOpenME library",
          "choices": [
            "9a01a05a5c7569f7"
          ],
          "uoa": "9a01a05a5c7569f7"
        }
      },
      "tags": [
        "64bits",
        "channel-stable",
        "compiled-by-gcc",
        "compiled-by-gcc-6.4.0",
        "host-os-linux-64",
        "lang-cpp",
        "lib",
        "nntest",
        "target-os-linux-64",
        "v0",
        "v0.1"
      ],
      "package_uoa": "a6f6a5e9a44c7999",
      "soft_alias": "lib.nntest",
      "setup": {
        "deps_compiler": "9698607419bb66de",
        "version_split": [
          0,
          1
        ],
        "target_os_uoa": "4258b5fe54828a50",
        "host_os_uoa": "4258b5fe54828a50",
        "deps_xopenme": "9a01a05a5c7569f7",
        "target_os_bits": "64",
        "version": "0.1"
      },
      "env_script": "env.sh"
    },
    "name": "NNTest library",
    "package_uoa": "a6f6a5e9a44c7999",
    "local": "yes"
  }
}
